pyezviz/DeviceSwitchType.py
pyezviz/__init__.py
pyezviz/__main__.py
pyezviz/camera.py
pyezviz/client.py
py_ezviz-0.1.7.4.dist-info/LICENSE
py_ezviz-0.1.7.4.dist-info/METADATA
py_ezviz-0.1.7.4.dist-info/WHEEL
py_ezviz-0.1.7.4.dist-info/entry_points.txt
py_ezviz-0.1.7.4.dist-info/top_level.txt
py_ezviz-0.1.7.4.dist-info/RECORD
